peatland_time_series/__init__.py
peatland_time_series/filter.py
peatland_time_series/sy.py
peatland_time_series/time_series.py
peatland_time_series/util.py
peatland_time_series/visualization.py
peatland_time_series-0.1.9.dist-info/WHEEL
peatland_time_series-0.1.9.dist-info/METADATA
peatland_time_series-0.1.9.dist-info/RECORD
