Metadata-Version: 2.1
Name: peatland-time-series
Version: 0.1.9
Summary: Analyze water retention in peatland from time series of precipitation and water table depth
Home-page: https://github.com/ulaval-rs/peatland-time-series
License: BSD-3-Clause
Keywords: text
Author: Gabriel Couture
Author-email: gacou54@ulaval.ca
Requires-Python: >=3.7.1,<3.11
Classifier: License :: OSI Approved :: BSD License
Classifier: Programming Language :: Python :: 3
Classifier: Programming Language :: Python :: 3.10
Classifier: Programming Language :: Python :: 3.8
Classifier: Programming Language :: Python :: 3.9
Requires-Dist: matplotlib (>=3.5.1,<4.0.0)
Requires-Dist: numpy (>=1.21.4,<2.0.0)
Requires-Dist: pandas (>=1.3.4,<2.0.0)
Requires-Dist: scipy (>=1.7.3,<2.0.0)
